QV/__init__.py
QV/context.py
QV/kind_of_quantity.py
QV/prefix.py
QV/quantity_value.py
QV/registered_unit.py
QV/scale.py
QV/signature.py
QV/unit_register.py
QV/units_dict.py
Quantity_Value-0.2.0.dist-info/AUTHORS.rst
Quantity_Value-0.2.0.dist-info/LICENSE
Quantity_Value-0.2.0.dist-info/METADATA
Quantity_Value-0.2.0.dist-info/WHEEL
Quantity_Value-0.2.0.dist-info/top_level.txt
Quantity_Value-0.2.0.dist-info/RECORD
