Metadata-Version: 2.1
Name: Quantity-Value
Version: 0.2.0
Summary: Quantity-Value supports calculations with physical quantities
Home-page: https://github.com/MSLNZ/Quantity-Value
Author: Measurement Standards Laboratory of New Zealand
Author-email: info@measurement.govt.nz
License: MIT
Platform: any
Classifier: Development Status :: 4 - Beta
Classifier: Intended Audience :: Science/Research
Classifier: Intended Audience :: Developers
Classifier: License :: OSI Approved :: MIT License
Classifier: Operating System :: OS Independent
Classifier: Programming Language :: Python :: 3
Classifier: Programming Language :: Python :: 3.5
Classifier: Programming Language :: Python :: 3.6
Classifier: Programming Language :: Python :: 3.7
Classifier: Programming Language :: Python :: 3.8
Classifier: Programming Language :: Python :: 3.9
Classifier: Topic :: Software Development
Classifier: Topic :: Scientific/Engineering
Requires-Dist: bidict
Provides-Extra: tests
Requires-Dist: pytest (>=4.4) ; extra == 'tests'
Requires-Dist: pytest-cov ; extra == 'tests'
Requires-Dist: sybil ; extra == 'tests'
